{"is_source_file": true, "format": "JavaScript", "description": "This file provides utility functions to access environment variables and configuration settings in a React frontend project. It includes methods for retrieving environment variables with default fallbacks, parsing feature flags, and obtaining URLs and environment-specific info.", "external_files": [], "external_methods": [], "published": ["getEnv", "getLogLevel", "getFeatureFlags", "getExperimentsEnabled", "getApiBase", "getBackendUrl", "getFrontendUrl", "getWsUrl", "getNodeEnv", "getPort", "getHealthPath"], "classes": [], "methods": [{"name": "getEnv(key, defaultValue = '')", "description": "Retrieves the environment variable for the given key, returning a default value if not set or invalid.", "scope": "", "scopeKind": ""}, {"name": "getLogLevel()", "description": "Returns the current log level based on environment variable 'REACT_APP_LOG_LEVEL', defaulting to 'info'.", "scope": "", "scopeKind": ""}, {"name": "getFeatureFlags()", "description": "Parses the feature flags from environment variable 'REACT_APP_FEATURE_FLAGS'; returns an object with flags set to true.", "scope": "", "scopeKind": ""}, {"name": "getExperimentsEnabled()", "description": "Returns whether experiments are enabled based on 'REACT_APP_EXPERIMENTS_ENABLED' environment variable.", "scope": "", "scopeKind": ""}, {"name": "getApiBase", "description": "Returns the API base URL from environment variable."}, {"name": "getBackendUrl", "description": "Returns the backend URL from environment variable."}, {"name": "getFrontendUrl", "description": "Returns the frontend URL from environment variable."}, {"name": "getWsUrl", "description": "Returns the WebSocket URL from environment variable."}, {"name": "getNodeEnv", "description": "Returns the node environment setting."}, {"name": "getPort", "description": "Returns the application port number as an integer."}, {"name": "getHealthPath", "description": "Returns the health check path URL."}], "calls": ["process.env", "JSON.parse"], "search-terms": ["environment variable access", "configuration", "React environment", "env utility functions", "feature flags", "API URLs", "log level setting"], "state": 2, "file_id": 25, "knowledge_revision": 56, "git_revision": "", "ctags": [{"_type": "tag", "name": "getApiBase", "path": "/home/kavia/workspace/code-generation/ecoliving-future-224178-224187/eco_cities_frontend/src/utils/env.js", "pattern": "/^export const getApiBase = () => getEnv('REACT_APP_API_BASE', '');$/", "language": "JavaScript", "kind": "constant"}, {"_type": "tag", "name": "getBackendUrl", "path": "/home/kavia/workspace/code-generation/ecoliving-future-224178-224187/eco_cities_frontend/src/utils/env.js", "pattern": "/^export const getBackendUrl = () => getEnv('REACT_APP_BACKEND_URL', '');$/", "language": "JavaScript", "kind": "constant"}, {"_type": "tag", "name": "getEnv", "path": "/home/kavia/workspace/code-generation/ecoliving-future-224178-224187/eco_cities_frontend/src/utils/env.js", "pattern": "/^export function getEnv(key, defaultValue = '') {$/", "language": "JavaScript", "kind": "function", "signature": "(key, defaultValue = '')"}, {"_type": "tag", "name": "getExperimentsEnabled", "path": "/home/kavia/workspace/code-generation/ecoliving-future-224178-224187/eco_cities_frontend/src/utils/env.js", "pattern": "/^export function getExperimentsEnabled() {$/", "language": "JavaScript", "kind": "function", "signature": "()"}, {"_type": "tag", "name": "getFeatureFlags", "path": "/home/kavia/workspace/code-generation/ecoliving-future-224178-224187/eco_cities_frontend/src/utils/env.js", "pattern": "/^export function getFeatureFlags() {$/", "language": "JavaScript", "kind": "function", "signature": "()"}, {"_type": "tag", "name": "getFrontendUrl", "path": "/home/kavia/workspace/code-generation/ecoliving-future-224178-224187/eco_cities_frontend/src/utils/env.js", "pattern": "/^export const getFrontendUrl = () => getEnv('REACT_APP_FRONTEND_URL', '');$/", "language": "JavaScript", "kind": "constant"}, {"_type": "tag", "name": "getHealthPath", "path": "/home/kavia/workspace/code-generation/ecoliving-future-224178-224187/eco_cities_frontend/src/utils/env.js", "pattern": "/^export const getHealthPath = () => getEnv('REACT_APP_HEALTHCHECK_PATH', '\\/health');$/", "language": "JavaScript", "kind": "constant"}, {"_type": "tag", "name": "getLogLevel", "path": "/home/kavia/workspace/code-generation/ecoliving-future-224178-224187/eco_cities_frontend/src/utils/env.js", "pattern": "/^export function getLogLevel() {$/", "language": "JavaScript", "kind": "function", "signature": "()"}, {"_type": "tag", "name": "getNodeEnv", "path": "/home/kavia/workspace/code-generation/ecoliving-future-224178-224187/eco_cities_frontend/src/utils/env.js", "pattern": "/^export const getNodeEnv = () => getEnv('REACT_APP_NODE_ENV', 'development');$/", "language": "JavaScript", "kind": "constant"}, {"_type": "tag", "name": "getPort", "path": "/home/kavia/workspace/code-generation/ecoliving-future-224178-224187/eco_cities_frontend/src/utils/env.js", "pattern": "/^export const getPort = () => Number(getEnv('REACT_APP_PORT', '3000')) || 3000;$/", "language": "JavaScript", "kind": "constant"}, {"_type": "tag", "name": "getWsUrl", "path": "/home/kavia/workspace/code-generation/ecoliving-future-224178-224187/eco_cities_frontend/src/utils/env.js", "pattern": "/^export const getWsUrl = () => getEnv('REACT_APP_WS_URL', '');$/", "language": "JavaScript", "kind": "constant"}, {"_type": "tag", "name": "safe", "path": "/home/kavia/workspace/code-generation/ecoliving-future-224178-224187/eco_cities_frontend/src/utils/env.js", "pattern": "/^const safe = (v, d = '') => (typeof v === 'string' && v.length ? v : d);$/", "language": "JavaScript", "kind": "constant"}], "hash": "46d7d0688e96de698a80ef05f1b07176", "format-version": 4, "code-base-name": "eco_cities_frontend", "filename": "eco_cities_frontend/src/utils/env.js", "revision_history": [{"56": ""}]}